Metadata-Version: 1.0
Name: obur
Version: 1.0.0
Summary: A minimalistic speed test library.
Home-page: https://github.com/muraty/obur
Author: Omer Murat Yildirim
Author-email: omermuratyildirim@gmail.com
License: BSD License
Keywords: speedtest speed obur puke
Platform: UNKNOWN
